pablo/__init__.py
pablo/client.py
pablo/endpoints.py
pablo/py.typed
pablo/resources.py
kiba_pablo_client-0.1.2.dist-info/METADATA
kiba_pablo_client-0.1.2.dist-info/WHEEL
kiba_pablo_client-0.1.2.dist-info/top_level.txt
kiba_pablo_client-0.1.2.dist-info/RECORD
