Metadata-Version: 2.1
Name: kiba-pablo-client
Version: 0.1.2
Summary: Pablo client
Home-page: https://github.com/kibalabs/pablo
License: UNKNOWN
Platform: UNKNOWN
Requires-Python: ~=3.7
Requires-Dist: kiba-core[requester] (>=0.3.0.dev0)
